{"olive oil": 908.0, "apples": 453.0, "water": 681.0, "chicken": 906.0, "eggs": 681.0, "lime": 681.0, "sour cream": 227.0, "bread": 1362.0, "canola oil": 681.0, "salsa": 227.0, "black beans": 227.0, "pickles": 227.0, "mint": 227.0, "shrimp": 453.0, "carrots": 906.0, "corn": 227.0, "peanut": 227.0, "turkey": 681.0, "shallot": 227.0, "spinach": 227.0, "tarragon": 227.0, "pork": 2265.0, "yogurt": 227.0, "sage": 454.0, "basil": 227.0, "flour": 227.0, "lettuce": 454.0, "chips": 227.0, "salad": 227.0, "ketchup": 227.0, "cabbage": 227.0, "alcohol": 227.0, "quince": 453.0}