{"chicken": 18120.0, "pistachio": 1816.0, "olive oil": 20657.0, "mint": 7718.0, "parsley": 8626.0, "chicory": 906.0, "fish": 5436.0, "almonds": 3405.0, "apricot": 3632.0, "lamb": 8607.0, "raisin": 2724.0, "pork": 1812.0, "shallot": 2951.0, "cucumber": 1589.0, "beef": 3171.0, "carrots": 4530.0, "lime": 2270.0, "chard": 453.0, "eggplant": 1359.0, "crookneck squash": 453.0, "water": 6810.0, "canola oil": 227.0, "broccoli": 3171.0, "basil": 1816.0, "peas": 1589.0, "turnips": 906.0, "sweet potatoes": 1359.0, "kohlrabi": 453.0, "spinach": 908.0, "asparagus": 453.0, "turkey": 227.0, "alcohol": 1589.0, "beans": 454.0, "sour cream": 227.0, "cashew": 227.0, "yogurt": 2497.0, "currant": 908.0, "eggs": 908.0, "cr\u00e8me fra\u00eeche": 227.0, "merguez sausage": 906.0, "collard": 453.0, "arugula": 227.0, "pumpkin": 454.0, "corn": 454.0, "buttermilk": 227.0, "mussels": 453.0, "shrimp": 453.0, "pineapple": 227.0, "coconut": 454.0, "leeks": 227.0, "margarine": 227.0, "pomegranate": 2497.0, "chorizo": 1359.0, "maple syrup": 227.0, "potatoes": 1812.0, "bread": 681.0, "scallops": 453.0, "flour": 454.0, "salad": 454.0, "tarragon": 227.0, "ketchup": 1135.0, "squash": 453.0, "cauliflower": 454.0, "kale": 454.0, "watercress": 454.0, "sage": 227.0, "meat": 681.0, "leaves": 227.0, "cranberries": 227.0, "hazelnut": 227.0, "goat": 227.0, "plum": 454.0, "grapes": 227.0, "walnut": 227.0, "passion fruit": 227.0, "X": 28.39}