{"lamb": 1812.0, "yogurt": 908.0, "frond": 227.0, "eggs": 15209.0, "almonds": 5448.0, "alcohol": 7945.0, "raisin": 9761.0, "cranberries": 2270.0, "olive oil": 7491.0, "parsnips": 906.0, "water": 2951.0, "plum": 454.0, "maple syrup": 227.0, "parsley": 2043.0, "shallot": 4086.0, "walnut": 2043.0, "fish": 2265.0, "cauliflower": 454.0, "carrots": 3171.0, "beef": 453.0, "pomegranate": 681.0, "coconut": 227.0, "fig": 1359.0, "apricot": 3632.0, "apples": 6342.0, "walnut oil": 227.0, "cabbage": 681.0, "pistachio": 681.0, "chicken": 4983.0, "bulgur": 681.0, "molasses": 454.0, "mint": 908.0, "peas": 227.0, "kale": 454.0, "cucumber": 454.0, "flour": 12258.0, "milk": 4540.0, "eggplant": 906.0, "chard": 453.0, "chicory": 906.0, "pear": 1359.0, "bread": 2497.0, "winter squash": 453.0, "turkey": 227.0, "spinach": 454.0, "chestnut": 454.0, "brussel sprouts": 453.0, "lime": 908.0, "oat": 681.0, "sour cream": 227.0, "cashew": 454.0, "sausage": 453.0, "venison": 453.0, "pecan": 227.0, "quinoa": 227.0, "hen": 906.0, "turnips": 906.0, "apple": 227.0, "meat": 227.0, "blueberries": 227.0, "merguez sausage": 453.0, "collard": 453.0, "pineapple": 454.0, "syrup": 454.0, "pork": 1359.0, "artichokes": 453.0, "tarragon": 227.0, "pumpkin": 454.0, "broccoli": 453.0, "rhubarb": 453.0, "buttermilk": 1135.0, "watercress": 227.0, "yam": 227.0, "arugula": 227.0, "corn": 227.0, "basil": 681.0, "coffee beans": 454.0, "lard": 681.0, "lettuce": 227.0, "prunes": 1589.0, "fruit": 227.0, "marmalade": 227.0, "semolina": 227.0, "leaves": 227.0, "margarine": 227.0, "ice cream": 227.0, "hazelnut": 227.0, "ketchup": 227.0, "cake": 227.0}