{"carrots": 453.0, "cabbage": 454.0, "spinach": 454.0, "turkey": 454.0, "radish": 1135.0, "corn": 1816.0, "lime": 8853.0, "pumpkin": 2270.0, "beans": 227.0, "salsa": 227.0, "alcohol": 1135.0, "chicken": 9513.0, "kale": 681.0, "olive oil": 6810.0, "pinto beans": 454.0, "fish": 3171.0, "squash": 453.0, "beef": 2265.0, "bread": 1362.0, "eggs": 1362.0, "cr\u00e8me fra\u00eeche": 681.0, "brine": 453.0, "scallions": 454.0, "yogurt": 454.0, "cucumber": 1362.0, "scallops": 453.0, "raisin": 681.0, "lard": 227.0, "mint": 1135.0, "shallot": 1135.0, "milk": 454.0, "walnut": 227.0, "pecan": 681.0, "chestnut": 227.0, "cashew": 227.0, "hazelnut": 227.0, "black beans": 681.0, "eggplant": 453.0, "lettuce": 454.0, "parsley": 908.0, "pattypan squash": 227.0, "tarragon": 227.0, "watercress": 227.0, "coffee beans": 227.0, "almonds": 454.0, "plum": 454.0, "peanut": 681.0, "plantain": 906.0, "potatoes": 453.0, "pork": 1359.0, "shrimp": 906.0, "water": 2043.0, "sour cream": 454.0, "buttermilk": 227.0, "flour": 227.0, "pear": 453.0, "apricot": 227.0, "leaves": 681.0, "canola oil": 227.0, "pomegranate": 227.0}