{"almonds": 1135.0, "olive oil": 26332.0, "parsley": 12258.0, "bread": 14755.0, "eggs": 12258.0, "carrots": 22197.0, "cabbage": 2270.0, "tomatillos": 906.0, "spinach": 3178.0, "radish": 908.0, "corn": 2270.0, "lime": 3859.0, "pumpkin": 1589.0, "ice cream": 227.0, "apples": 4530.0, "sour cream": 2043.0, "brine": 453.0, "chicken": 35787.0, "maple syrup": 1135.0, "cannellini beans": 906.0, "alcohol": 14074.0, "yogurt": 2270.0, "cornmeal": 1589.0, "sage": 8626.0, "shallot": 7945.0, "sausage": 4077.0, "flour": 4313.0, "sprouts": 454.0, "cranberries": 3405.0, "meat": 3405.0, "buttermilk": 1135.0, "chips": 681.0, "cake": 454.0, "cucumber": 908.0, "mint": 2724.0, "peanut": 1362.0, "fish": 3171.0, "scallions": 681.0, "lettuce": 2497.0, "hazelnut": 1135.0, "collard": 906.0, "pecan": 1135.0, "oyster": 453.0, "kimchi": 227.0, "baby bok choy": 453.0, "black beans": 908.0, "broccoli": 1359.0, "pear": 1359.0, "pomegranate": 681.0, "chicory": 1812.0, "seaweed": 227.0, "water": 8626.0, "sweet potatoes": 1359.0, "leeks": 2724.0, "potatoes": 7248.0, "milk": 4086.0, "pinto beans": 454.0, "chestnut": 2270.0, "pork": 5436.0, "arugula": 681.0, "rye": 227.0, "pickles": 454.0, "duck ": 454.0, "kale": 908.0, "salsa": 908.0, "chard": 906.0, "grapes": 681.0, "apricot": 454.0, "raisin": 908.0, "tarragon": 3405.0, "quinoa": 227.0, "yam": 1589.0, "brussel sprouts": 2718.0, "peas": 1362.0, "currant": 227.0, "parsnips": 1359.0, "coffee beans": 227.0, "lard": 454.0, "beans": 1362.0, "lobster": 906.0, "molasses": 454.0, "mango": 454.0, "italian sausage": 906.0, "ketchup": 1589.0, "X": 56.78, "barley": 227.0, "jicama": 453.0, "basil": 1362.0, "coleslaw": 681.0, "canola oil": 681.0, "grits": 227.0, "plum": 227.0, "walnut": 1362.0, "blueberries": 227.0, "mussels": 453.0, "escarole": 454.0, "coconut": 681.0, "caramel": 227.0, "cr\u00e8me fra\u00eeche": 227.0, "beef": 1359.0, "crackers": 227.0, "watercress": 908.0, "cashew": 227.0, "apple": 227.0, "shortening": 454.0, "turnips": 906.0, "beet": 453.0, "semolina": 227.0, "artichokes": 453.0, "lamb": 453.0, "walnut oil": 227.0, "winter squash": 453.0, "bulgur": 227.0, "leaves": 908.0, "pistachio": 454.0, "squash": 453.0, "sunflower seeds": 227.0, "salad": 227.0}